CHANGELOG.md
MANIFEST.in
README.rst
setup.cfg
setup.py
Messkit.egg-info/PKG-INFO
Messkit.egg-info/SOURCES.txt
Messkit.egg-info/dependency_links.txt
Messkit.egg-info/entry_points.txt
Messkit.egg-info/requires.txt
Messkit.egg-info/top_level.txt
messkit/__init__.py
messkit/_version.py
messkit/commands.py
messkit/config.py
messkit/enum.py
messkit/db/__init__.py
messkit/db/model.py
messkit/web/__init__.py
messkit/web/app.py
messkit/web/menus.py
messkit/web/subscribers.py
messkit/web/static/__init__.py
messkit/web/static/img/messkit-small.png
messkit/web/static/img/messkit.png
messkit/web/views/__init__.py