Metadata-Version: 2.1
Name: Messkit
Version: 0.1.8
Summary: Generic-ish Data Utility App
Home-page: https://rattailproject.org
Author: Lance Edgar
Author-email: lance@edbob.org
Classifier: Development Status :: 3 - Alpha
Classifier: Environment :: Console
Classifier: Environment :: Web Environment
Classifier: Framework :: Pyramid
Classifier: Intended Audience :: Developers
Classifier: Natural Language :: English
Classifier: Operating System :: POSIX :: Linux
Classifier: Programming Language :: Python
Classifier: Programming Language :: Python :: 3
Classifier: Topic :: Office/Business
Requires-Dist: mysql-connector-python
Requires-Dist: psycopg2
Requires-Dist: prompt_toolkit
Requires-Dist: rich
Requires-Dist: Sphinx
Requires-Dist: Tailbone
